oneworld/__init__.py
oneworld/__init__.pyc
oneworld/smap.py
oneworld/smap.pyc
oneworld/utils.py
oneworld/utils.pyc
oneworld/web_classes.py
oneworld/web_classes.pyc
oneworld/wmap.py
oneworld/wmap.pyc
oneworld/__pycache__/__init__.cpython-310.pyc
oneworld/__pycache__/__init__.cpython-37.pyc
oneworld/__pycache__/smap.cpython-310.pyc
oneworld/__pycache__/smap.cpython-37.pyc
oneworld/__pycache__/utils.cpython-310.pyc
oneworld/__pycache__/utils.cpython-37.pyc
oneworld/__pycache__/web_classes.cpython-310.pyc
oneworld/__pycache__/web_classes.cpython-37.pyc
oneworld/__pycache__/wmap.cpython-310.pyc
oneworld/__pycache__/wmap.cpython-37.pyc
oneworld/templates/basemap.html
oneworld/templates/box.html
oneworld/templates/circles.html
oneworld/templates/colorbar.html
oneworld/templates/geojson.html
oneworld/templates/heatmap.html
oneworld/templates/lines.html
oneworld/templates/logo.html
oneworld/templates/markers.html
oneworld/templates/network.html
oneworld/templates/panel.html
oneworld/templates/world.html
oneworld-1.0.7.dist-info/LICENSE
oneworld-1.0.7.dist-info/METADATA
oneworld-1.0.7.dist-info/WHEEL
oneworld-1.0.7.dist-info/top_level.txt
oneworld-1.0.7.dist-info/RECORD
