Metadata-Version: 2.1
Name: oneworld
Version: 1.0.7
Summary: Python mapping made easy
Home-page: https://taguilar@bitbucket.org/taguilar/oneworld
Author: Antoni Aguilar Mogas
Author-email: aguilar.mogas@gmail.com
Classifier: Programming Language :: Python :: 3
Classifier: License :: OSI Approved :: MIT License
Classifier: Operating System :: OS Independent
Classifier: Intended Audience :: Science/Research
Classifier: Topic :: Scientific/Engineering :: Visualization
Classifier: Topic :: Scientific/Engineering :: GIS
Requires-Python: >=3.7
License-File: LICENSE
Requires-Dist: pandas (>=1.5.2)
Requires-Dist: matplotlib (>=3.6.2)
Requires-Dist: seaborn (>=0.12.2)
Requires-Dist: jinja2 (>=3.1.2)
Requires-Dist: cartopy (>=0.21.1)
